[
    {
        "jmhVersion" : "1.37",
        "benchmark" : "io.prometheus.metrics.benchmarks.CounterBenchmark.codahaleIncNoLabels",
        "mode" : "thrpt",
        "threads" : 4,
        "forks" : 3,
        "jvm" : "/home/runner/.local/share/mise/installs/java/temurin-25.0.2+10.0.LTS/bin/java",
        "jvmArgs" : [
        ],
        "jdkVersion" : "25.0.2",
        "vmName" : "OpenJDK 64-Bit Server VM",
        "vmVersion" : "25.0.2+10-LTS",
        "warmupIterations" : 3,
        "warmupTime" : "10 s",
        "warmupBatchSize" : 1,
        "measurementIterations" : 5,
        "measurementTime" : "10 s",
        "measurementBatchSize" : 1,
        "primaryMetric" : {
            "score" : 48247.6683746726,
            "scoreError" : 865.4117028126891,
            "scoreConfidence" : [
                47382.25667185991,
                49113.08007748528
            ],
            "scorePercentiles" : {
                "0.0" : 47202.3349150712,
                "50.0" : 48232.74023271609,
                "90.0" : 49252.88975627401,
                "95.0" : 49262.64664334877,
                "99.0" : 49262.64664334877,
                "99.9" : 49262.64664334877,
                "99.99" : 49262.64664334877,
                "99.999" : 49262.64664334877,
                "99.9999" : 49262.64664334877,
                "100.0" : 49262.64664334877
            },
            "scoreUnit" : "ops/s",
            "rawData" : [
                [
                    48232.34029992599,
                    48270.102877162324,
                    48120.70309271375,
                    48271.77189176633,
                    48232.74023271609
                ],
                [
                    49116.20872112607,
                    49246.38516489084,
                    49213.457351878256,
                    49262.64664334877,
                    49232.145404635936
                ],
                [
                    47313.29004649288,
                    47344.91093485303,
                    47316.32621285411,
                    47339.66183065325,
                    47202.3349150712
                ]
            ]
        },
        "secondaryMetrics" : {
        }
    },
    {
        "jmhVersion" : "1.37",
        "benchmark" : "io.prometheus.metrics.benchmarks.CounterBenchmark.openTelemetryAdd",
        "mode" : "thrpt",
        "threads" : 4,
        "forks" : 3,
        "jvm" : "/home/runner/.local/share/mise/installs/java/temurin-25.0.2+10.0.LTS/bin/java",
        "jvmArgs" : [
        ],
        "jdkVersion" : "25.0.2",
        "vmName" : "OpenJDK 64-Bit Server VM",
        "vmVersion" : "25.0.2+10-LTS",
        "warmupIterations" : 3,
        "warmupTime" : "10 s",
        "warmupBatchSize" : 1,
        "measurementIterations" : 5,
        "measurementTime" : "10 s",
        "measurementBatchSize" : 1,
        "primaryMetric" : {
            "score" : 1437.0862763812263,
            "scoreError" : 213.68738731387367,
            "scoreConfidence" : [
                1223.3988890673527,
                1650.7736636951
            ],
            "scorePercentiles" : {
                "0.0" : 1240.4955441880504,
                "50.0" : 1372.552900030913,
                "90.0" : 1718.1323888711806,
                "95.0" : 1768.265634676011,
                "99.0" : 1768.265634676011,
                "99.9" : 1768.265634676011,
                "99.99" : 1768.265634676011,
                "99.999" : 1768.265634676011,
                "99.9999" : 1768.265634676011,
                "100.0" : 1768.265634676011
            },
            "scoreUnit" : "ops/s",
            "rawData" : [
                [
                    1679.4710794993612,
                    1678.7696014774592,
                    1677.731823778954,
                    1684.7102250012936,
                    1768.265634676011
                ],
                [
                    1372.8044623179765,
                    1372.3868251336303,
                    1372.8185290822928,
                    1372.552900030913,
                    1372.3545622102286
                ],
                [
                    1240.4955441880504,
                    1240.5555772569026,
                    1240.6596982710516,
                    1240.8546673646283,
                    1241.8630154296438
                ]
            ]
        },
        "secondaryMetrics" : {
        }
    },
    {
        "jmhVersion" : "1.37",
        "benchmark" : "io.prometheus.metrics.benchmarks.CounterBenchmark.openTelemetryInc",
        "mode" : "thrpt",
        "threads" : 4,
        "forks" : 3,
        "jvm" : "/home/runner/.local/share/mise/installs/java/temurin-25.0.2+10.0.LTS/bin/java",
        "jvmArgs" : [
        ],
        "jdkVersion" : "25.0.2",
        "vmName" : "OpenJDK 64-Bit Server VM",
        "vmVersion" : "25.0.2+10-LTS",
        "warmupIterations" : 3,
        "warmupTime" : "10 s",
        "warmupBatchSize" : 1,
        "measurementIterations" : 5,
        "measurementTime" : "10 s",
        "measurementBatchSize" : 1,
        "primaryMetric" : {
            "score" : 1359.9722377196615,
            "scoreError" : 178.06820750859436,
            "scoreConfidence" : [
                1181.904030211067,
                1538.040445228256
            ],
            "scorePercentiles" : {
                "0.0" : 1234.7430584631445,
                "50.0" : 1257.8220654331865,
                "90.0" : 1588.3653980762779,
                "95.0" : 1588.665748403124,
                "99.0" : 1588.665748403124,
                "99.9" : 1588.665748403124,
                "99.99" : 1588.665748403124,
                "99.999" : 1588.665748403124,
                "99.9999" : 1588.665748403124,
                "100.0" : 1588.665748403124
            },
            "scoreUnit" : "ops/s",
            "rawData" : [
                [
                    1257.6789271165671,
                    1257.5283667553276,
                    1258.0254473442237,
                    1257.8220654331865,
                    1257.930083728528
                ],
                [
                    1583.1817866581764,
                    1588.665748403124,
                    1587.87311676711,
                    1587.8911027568965,
                    1588.165164525047
                ],
                [
                    1235.1423103453524,
                    1234.8777936049207,
                    1234.7430584631445,
                    1234.91875889843,
                    1235.139834994885
                ]
            ]
        },
        "secondaryMetrics" : {
        }
    },
    {
        "jmhVersion" : "1.37",
        "benchmark" : "io.prometheus.metrics.benchmarks.CounterBenchmark.openTelemetryIncNoLabels",
        "mode" : "thrpt",
        "threads" : 4,
        "forks" : 3,
        "jvm" : "/home/runner/.local/share/mise/installs/java/temurin-25.0.2+10.0.LTS/bin/java",
        "jvmArgs" : [
        ],
        "jdkVersion" : "25.0.2",
        "vmName" : "OpenJDK 64-Bit Server VM",
        "vmVersion" : "25.0.2+10-LTS",
        "warmupIterations" : 3,
        "warmupTime" : "10 s",
        "warmupBatchSize" : 1,
        "measurementIterations" : 5,
        "measurementTime" : "10 s",
        "measurementBatchSize" : 1,
        "primaryMetric" : {
            "score" : 1311.5267696817816,
            "scoreError" : 133.77730360654374,
            "scoreConfidence" : [
                1177.749466075238,
                1445.3040732883253
            ],
            "scorePercentiles" : {
                "0.0" : 1213.9952666986007,
                "50.0" : 1237.967347549088,
                "90.0" : 1482.4540074494096,
                "95.0" : 1482.493096048412,
                "99.0" : 1482.493096048412,
                "99.9" : 1482.493096048412,
                "99.99" : 1482.493096048412,
                "99.999" : 1482.493096048412,
                "99.9999" : 1482.493096048412,
                "100.0" : 1482.493096048412
            },
            "scoreUnit" : "ops/s",
            "rawData" : [
                [
                    1482.493096048412,
                    1481.140122206287,
                    1481.8428721583655,
                    1481.938396130901,
                    1482.4279483834077
                ],
                [
                    1215.2953368640308,
                    1213.9952666986007,
                    1214.4896802789306,
                    1214.9762056823406,
                    1214.809466055248
                ],
                [
                    1237.9044455855092,
                    1237.988021782703,
                    1237.967347549088,
                    1238.0504038255274,
                    1237.582935977371
                ]
            ]
        },
        "secondaryMetrics" : {
        }
    },
    {
        "jmhVersion" : "1.37",
        "benchmark" : "io.prometheus.metrics.benchmarks.CounterBenchmark.prometheusAdd",
        "mode" : "thrpt",
        "threads" : 4,
        "forks" : 3,
        "jvm" : "/home/runner/.local/share/mise/installs/java/temurin-25.0.2+10.0.LTS/bin/java",
        "jvmArgs" : [
        ],
        "jdkVersion" : "25.0.2",
        "vmName" : "OpenJDK 64-Bit Server VM",
        "vmVersion" : "25.0.2+10-LTS",
        "warmupIterations" : 3,
        "warmupTime" : "10 s",
        "warmupBatchSize" : 1,
        "measurementIterations" : 5,
        "measurementTime" : "10 s",
        "measurementBatchSize" : 1,
        "primaryMetric" : {
            "score" : 51098.61517241378,
            "scoreError" : 532.7765869032088,
            "scoreConfidence" : [
                50565.83858551057,
                51631.39175931699
            ],
            "scorePercentiles" : {
                "0.0" : 50325.02431027292,
                "50.0" : 51360.050983243,
                "90.0" : 51554.90322038909,
                "95.0" : 51564.85655077023,
                "99.0" : 51564.85655077023,
                "99.9" : 51564.85655077023,
                "99.99" : 51564.85655077023,
                "99.999" : 51564.85655077023,
                "99.9999" : 51564.85655077023,
                "100.0" : 51564.85655077023
            },
            "scoreUnit" : "ops/s",
            "rawData" : [
                [
                    51351.92064945272,
                    51360.050983243,
                    51266.298127222035,
                    51398.68218797048,
                    51393.9111187399
                ],
                [
                    51372.82666671964,
                    51537.8510233093,
                    51564.85655077023,
                    51548.26766680166,
                    51539.35083249428
                ],
                [
                    50415.79411566478,
                    50463.343083089,
                    50473.06701809762,
                    50467.98325235931,
                    50325.02431027292
                ]
            ]
        },
        "secondaryMetrics" : {
        }
    },
    {
        "jmhVersion" : "1.37",
        "benchmark" : "io.prometheus.metrics.benchmarks.CounterBenchmark.prometheusInc",
        "mode" : "thrpt",
        "threads" : 4,
        "forks" : 3,
        "jvm" : "/home/runner/.local/share/mise/installs/java/temurin-25.0.2+10.0.LTS/bin/java",
        "jvmArgs" : [
        ],
        "jdkVersion" : "25.0.2",
        "vmName" : "OpenJDK 64-Bit Server VM",
        "vmVersion" : "25.0.2+10-LTS",
        "warmupIterations" : 3,
        "warmupTime" : "10 s",
        "warmupBatchSize" : 1,
        "measurementIterations" : 5,
        "measurementTime" : "10 s",
        "measurementBatchSize" : 1,
        "primaryMetric" : {
            "score" : 65877.21486137956,
            "scoreError" : 1921.459596477916,
            "scoreConfidence" : [
                63955.75526490164,
                67798.67445785747
            ],
            "scorePercentiles" : {
                "0.0" : 63391.54690426999,
                "50.0" : 66647.44331123425,
                "90.0" : 67599.25870270639,
                "95.0" : 67628.36656048096,
                "99.0" : 67628.36656048096,
                "99.9" : 67628.36656048096,
                "99.99" : 67628.36656048096,
                "99.999" : 67628.36656048096,
                "99.9999" : 67628.36656048096,
                "100.0" : 67628.36656048096
            },
            "scoreUnit" : "ops/s",
            "rawData" : [
                [
                    66647.44331123425,
                    66651.23605899341,
                    66452.38451328732,
                    66648.42064920998,
                    66628.2170993819
                ],
                [
                    67414.17352376269,
                    67628.36656048096,
                    67562.60829341365,
                    67579.85346418999,
                    67524.45067760028
                ],
                [
                    63519.60717771007,
                    63391.54690426999,
                    63543.39457736841,
                    63574.116733829665,
                    63392.40337596078
                ]
            ]
        },
        "secondaryMetrics" : {
        }
    },
    {
        "jmhVersion" : "1.37",
        "benchmark" : "io.prometheus.metrics.benchmarks.CounterBenchmark.prometheusNoLabelsInc",
        "mode" : "thrpt",
        "threads" : 4,
        "forks" : 3,
        "jvm" : "/home/runner/.local/share/mise/installs/java/temurin-25.0.2+10.0.LTS/bin/java",
        "jvmArgs" : [
        ],
        "jdkVersion" : "25.0.2",
        "vmName" : "OpenJDK 64-Bit Server VM",
        "vmVersion" : "25.0.2+10-LTS",
        "warmupIterations" : 3,
        "warmupTime" : "10 s",
        "warmupBatchSize" : 1,
        "measurementIterations" : 5,
        "measurementTime" : "10 s",
        "measurementBatchSize" : 1,
        "primaryMetric" : {
            "score" : 56632.4963183877,
            "scoreError" : 1075.682563249052,
            "scoreConfidence" : [
                55556.813755138646,
                57708.17888163675
            ],
            "scorePercentiles" : {
                "0.0" : 55159.72002529433,
                "50.0" : 57254.238191261094,
                "90.0" : 57476.404943895745,
                "95.0" : 57480.951663575026,
                "99.0" : 57480.951663575026,
                "99.9" : 57480.951663575026,
                "99.99" : 57480.951663575026,
                "99.999" : 57480.951663575026,
                "99.9999" : 57480.951663575026,
                "100.0" : 57480.951663575026
            },
            "scoreUnit" : "ops/s",
            "rawData" : [
                [
                    57473.37379744289,
                    57480.951663575026,
                    57318.75034281038,
                    57330.92025165511,
                    57454.18962611101
                ],
                [
                    55159.72002529433,
                    55308.67527310969,
                    55266.180796493296,
                    55289.64670102837,
                    55301.88769288282
                ],
                [
                    57229.20788130723,
                    57265.380584147635,
                    57262.181878391,
                    57254.238191261094,
                    57092.14007030568
                ]
            ]
        },
        "secondaryMetrics" : {
        }
    },
    {
        "jmhVersion" : "1.37",
        "benchmark" : "io.prometheus.metrics.benchmarks.CounterBenchmark.simpleclientAdd",
        "mode" : "thrpt",
        "threads" : 4,
        "forks" : 3,
        "jvm" : "/home/runner/.local/share/mise/installs/java/temurin-25.0.2+10.0.LTS/bin/java",
        "jvmArgs" : [
        ],
        "jdkVersion" : "25.0.2",
        "vmName" : "OpenJDK 64-Bit Server VM",
        "vmVersion" : "25.0.2+10-LTS",
        "warmupIterations" : 3,
        "warmupTime" : "10 s",
        "warmupBatchSize" : 1,
        "measurementIterations" : 5,
        "measurementTime" : "10 s",
        "measurementBatchSize" : 1,
        "primaryMetric" : {
            "score" : 6330.857345133847,
            "scoreError" : 175.74893423733454,
            "scoreConfidence" : [
                6155.108410896512,
                6506.606279371182
            ],
            "scorePercentiles" : {
                "0.0" : 6186.51086012161,
                "50.0" : 6228.363479428665,
                "90.0" : 6558.867090733106,
                "95.0" : 6559.160392455826,
                "99.0" : 6559.160392455826,
                "99.9" : 6559.160392455826,
                "99.99" : 6559.160392455826,
                "99.999" : 6559.160392455826,
                "99.9999" : 6559.160392455826,
                "100.0" : 6559.160392455826
            },
            "scoreUnit" : "ops/s",
            "rawData" : [
                [
                    6228.363479428665,
                    6228.581578361338,
                    6213.906484871939,
                    6230.353428394475,
                    6213.851277426332
                ],
                [
                    6542.950238029067,
                    6558.671556251294,
                    6556.746795686558,
                    6557.137741437373,
                    6559.160392455826
                ],
                [
                    6225.91031910922,
                    6224.340159903082,
                    6186.51086012161,
                    6225.619070485223,
                    6210.756795045726
                ]
            ]
        },
        "secondaryMetrics" : {
        }
    },
    {
        "jmhVersion" : "1.37",
        "benchmark" : "io.prometheus.metrics.benchmarks.CounterBenchmark.simpleclientInc",
        "mode" : "thrpt",
        "threads" : 4,
        "forks" : 3,
        "jvm" : "/home/runner/.local/share/mise/installs/java/temurin-25.0.2+10.0.LTS/bin/java",
        "jvmArgs" : [
        ],
        "jdkVersion" : "25.0.2",
        "vmName" : "OpenJDK 64-Bit Server VM",
        "vmVersion" : "25.0.2+10-LTS",
        "warmupIterations" : 3,
        "warmupTime" : "10 s",
        "warmupBatchSize" : 1,
        "measurementIterations" : 5,
        "measurementTime" : "10 s",
        "measurementBatchSize" : 1,
        "primaryMetric" : {
            "score" : 6683.9874184021355,
            "scoreError" : 116.4571090742164,
            "scoreConfidence" : [
                6567.530309327919,
                6800.444527476352
            ],
            "scorePercentiles" : {
                "0.0" : 6522.146412677248,
                "50.0" : 6756.121343971356,
                "90.0" : 6766.780510088582,
                "95.0" : 6767.127626653339,
                "99.0" : 6767.127626653339,
                "99.9" : 6767.127626653339,
                "99.99" : 6767.127626653339,
                "99.999" : 6767.127626653339,
                "99.9999" : 6767.127626653339,
                "100.0" : 6767.127626653339
            },
            "scoreUnit" : "ops/s",
            "rawData" : [
                [
                    6756.121343971356,
                    6758.915106095268,
                    6741.301011176695,
                    6760.16796821576,
                    6758.249226511635
                ],
                [
                    6748.584620650165,
                    6766.549099045411,
                    6764.887343585637,
                    6760.280902653945,
                    6767.127626653339
                ],
                [
                    6541.604717321977,
                    6540.002764896226,
                    6536.525975232425,
                    6537.347157344961,
                    6522.146412677248
                ]
            ]
        },
        "secondaryMetrics" : {
        }
    },
    {
        "jmhVersion" : "1.37",
        "benchmark" : "io.prometheus.metrics.benchmarks.CounterBenchmark.simpleclientNoLabelsInc",
        "mode" : "thrpt",
        "threads" : 4,
        "forks" : 3,
        "jvm" : "/home/runner/.local/share/mise/installs/java/temurin-25.0.2+10.0.LTS/bin/java",
        "jvmArgs" : [
        ],
        "jdkVersion" : "25.0.2",
        "vmName" : "OpenJDK 64-Bit Server VM",
        "vmVersion" : "25.0.2+10-LTS",
        "warmupIterations" : 3,
        "warmupTime" : "10 s",
        "warmupBatchSize" : 1,
        "measurementIterations" : 5,
        "measurementTime" : "10 s",
        "measurementBatchSize" : 1,
        "primaryMetric" : {
            "score" : 6356.173331485622,
            "scoreError" : 74.54869408138362,
            "scoreConfidence" : [
                6281.6246374042385,
                6430.722025567005
            ],
            "scorePercentiles" : {
                "0.0" : 6273.260004235541,
                "50.0" : 6344.325795804843,
                "90.0" : 6451.250048292918,
                "95.0" : 6452.128717747202,
                "99.0" : 6452.128717747202,
                "99.9" : 6452.128717747202,
                "99.99" : 6452.128717747202,
                "99.999" : 6452.128717747202,
                "99.9999" : 6452.128717747202,
                "100.0" : 6452.128717747202
            },
            "scoreUnit" : "ops/s",
            "rawData" : [
                [
                    6282.380969087252,
                    6278.959545876108,
                    6273.260004235541,
                    6284.053775462534,
                    6283.426506178377
                ],
                [
                    6344.093354727082,
                    6345.338048158777,
                    6344.112910520567,
                    6344.749104973668,
                    6344.325795804843
                ],
                [
                    6450.2319927283625,
                    6450.664268656728,
                    6434.325826717017,
                    6430.549151410276,
                    6452.128717747202
                ]
            ]
        },
        "secondaryMetrics" : {
        }
    },
    {
        "jmhVersion" : "1.37",
        "benchmark" : "io.prometheus.metrics.benchmarks.HistogramBenchmark.openTelemetryClassic",
        "mode" : "thrpt",
        "threads" : 4,
        "forks" : 3,
        "jvm" : "/home/runner/.local/share/mise/installs/java/temurin-25.0.2+10.0.LTS/bin/java",
        "jvmArgs" : [
        ],
        "jdkVersion" : "25.0.2",
        "vmName" : "OpenJDK 64-Bit Server VM",
        "vmVersion" : "25.0.2+10-LTS",
        "warmupIterations" : 3,
        "warmupTime" : "10 s",
        "warmupBatchSize" : 1,
        "measurementIterations" : 5,
        "measurementTime" : "10 s",
        "measurementBatchSize" : 1,
        "primaryMetric" : {
            "score" : 675.3784564205639,
            "scoreError" : 50.044871827796946,
            "scoreConfidence" : [
                625.333584592767,
                725.4233282483608
            ],
            "scorePercentiles" : {
                "0.0" : 617.8184135893723,
                "50.0" : 693.706249405647,
                "90.0" : 729.681366551211,
                "95.0" : 729.7346223672841,
                "99.0" : 729.7346223672841,
                "99.9" : 729.7346223672841,
                "99.99" : 729.7346223672841,
                "99.999" : 729.7346223672841,
                "99.9999" : 729.7346223672841,
                "100.0" : 729.7346223672841
            },
            "scoreUnit" : "ops/s",
            "rawData" : [
                [
                    693.706249405647,
                    695.2728562431749,
                    695.3937788487934,
                    658.763447890556,
                    659.6184691048068
                ],
                [
                    724.8036034368837,
                    729.6458626738289,
                    729.7346223672841,
                    723.6242890263435,
                    725.0355357655445
                ],
                [
                    619.351834069227,
                    619.1585347600355,
                    617.8184135893723,
                    620.0092543296065,
                    618.7400947973564
                ]
            ]
        },
        "secondaryMetrics" : {
        }
    },
    {
        "jmhVersion" : "1.37",
        "benchmark" : "io.prometheus.metrics.benchmarks.HistogramBenchmark.openTelemetryExponential",
        "mode" : "thrpt",
        "threads" : 4,
        "forks" : 3,
        "jvm" : "/home/runner/.local/share/mise/installs/java/temurin-25.0.2+10.0.LTS/bin/java",
        "jvmArgs" : [
        ],
        "jdkVersion" : "25.0.2",
        "vmName" : "OpenJDK 64-Bit Server VM",
        "vmVersion" : "25.0.2+10-LTS",
        "warmupIterations" : 3,
        "warmupTime" : "10 s",
        "warmupBatchSize" : 1,
        "measurementIterations" : 5,
        "measurementTime" : "10 s",
        "measurementBatchSize" : 1,
        "primaryMetric" : {
            "score" : 517.046090488867,
            "scoreError" : 24.151406926078486,
            "scoreConfidence" : [
                492.8946835627885,
                541.1974974149455
            ],
            "scorePercentiles" : {
                "0.0" : 486.5424308955361,
                "50.0" : 524.10506345529,
                "90.0" : 540.0790551501144,
                "95.0" : 540.1637162069651,
                "99.0" : 540.1637162069651,
                "99.9" : 540.1637162069651,
                "99.99" : 540.1637162069651,
                "99.999" : 540.1637162069651,
                "99.9999" : 540.1637162069651,
                "100.0" : 540.1637162069651
            },
            "scoreUnit" : "ops/s",
            "rawData" : [
                [
                    486.5424308955361,
                    488.2534069397376,
                    487.5379769254362,
                    487.81704324844463,
                    487.5451344805506
                ],
                [
                    540.0226144455472,
                    540.1637162069651,
                    539.1196092102749,
                    539.2674799720853,
                    539.5383623102233
                ],
                [
                    523.265676156936,
                    523.8559284732864,
                    524.10506345529,
                    524.3744555269303,
                    524.2824590857599
                ]
            ]
        },
        "secondaryMetrics" : {
        }
    },
    {
        "jmhVersion" : "1.37",
        "benchmark" : "io.prometheus.metrics.benchmarks.HistogramBenchmark.prometheusClassic",
        "mode" : "thrpt",
        "threads" : 4,
        "forks" : 3,
        "jvm" : "/home/runner/.local/share/mise/installs/java/temurin-25.0.2+10.0.LTS/bin/java",
        "jvmArgs" : [
        ],
        "jdkVersion" : "25.0.2",
        "vmName" : "OpenJDK 64-Bit Server VM",
        "vmVersion" : "25.0.2+10-LTS",
        "warmupIterations" : 3,
        "warmupTime" : "10 s",
        "warmupBatchSize" : 1,
        "measurementIterations" : 5,
        "measurementTime" : "10 s",
        "measurementBatchSize" : 1,
        "primaryMetric" : {
            "score" : 5552.451592212058,
            "scoreError" : 1528.796965812545,
            "scoreConfidence" : [
                4023.6546263995133,
                7081.248558024603
            ],
            "scorePercentiles" : {
                "0.0" : 4108.808578735387,
                "50.0" : 4982.017391661476,
                "90.0" : 7399.513362971669,
                "95.0" : 7400.7272822880805,
                "99.0" : 7400.7272822880805,
                "99.9" : 7400.7272822880805,
                "99.99" : 7400.7272822880805,
                "99.999" : 7400.7272822880805,
                "99.9999" : 7400.7272822880805,
                "100.0" : 7400.7272822880805
            },
            "scoreUnit" : "ops/s",
            "rawData" : [
                [
                    7400.7272822880805,
                    7385.574007459403,
                    7388.111701688218,
                    7396.066983426802,
                    7398.704083427396
                ],
                [
                    4978.4957526126855,
                    4974.943303178603,
                    4982.017391661476,
                    5034.062710943755,
                    5784.8804028008635
                ],
                [
                    4110.938525890526,
                    4113.180912940304,
                    4115.074213214755,
                    4115.188032912617,
                    4108.808578735387
                ]
            ]
        },
        "secondaryMetrics" : {
        }
    },
    {
        "jmhVersion" : "1.37",
        "benchmark" : "io.prometheus.metrics.benchmarks.HistogramBenchmark.prometheusNative",
        "mode" : "thrpt",
        "threads" : 4,
        "forks" : 3,
        "jvm" : "/home/runner/.local/share/mise/installs/java/temurin-25.0.2+10.0.LTS/bin/java",
        "jvmArgs" : [
        ],
        "jdkVersion" : "25.0.2",
        "vmName" : "OpenJDK 64-Bit Server VM",
        "vmVersion" : "25.0.2+10-LTS",
        "warmupIterations" : 3,
        "warmupTime" : "10 s",
        "warmupBatchSize" : 1,
        "measurementIterations" : 5,
        "measurementTime" : "10 s",
        "measurementBatchSize" : 1,
        "primaryMetric" : {
            "score" : 3157.7026313752363,
            "scoreError" : 142.88321861956877,
            "scoreConfidence" : [
                3014.8194127556676,
                3300.585849994805
            ],
            "scorePercentiles" : {
                "0.0" : 2780.3479837433115,
                "50.0" : 3206.098630107308,
                "90.0" : 3275.64982045598,
                "95.0" : 3303.0910368657883,
                "99.0" : 3303.0910368657883,
                "99.9" : 3303.0910368657883,
                "99.99" : 3303.0910368657883,
                "99.999" : 3303.0910368657883,
                "99.9999" : 3303.0910368657883,
                "100.0" : 3303.0910368657883
            },
            "scoreUnit" : "ops/s",
            "rawData" : [
                [
                    3207.6056238622623,
                    3147.979046289157,
                    3111.9900951705545,
                    3123.8533123723655,
                    3303.0910368657883
                ],
                [
                    3186.026823997728,
                    3257.355676182774,
                    3255.128642124675,
                    3256.682712473754,
                    3206.098630107308
                ],
                [
                    3005.2287273276957,
                    3251.699397661405,
                    3223.858966383075,
                    3048.592796066693,
                    2780.3479837433115
                ]
            ]
        },
        "secondaryMetrics" : {
        }
    },
    {
        "jmhVersion" : "1.37",
        "benchmark" : "io.prometheus.metrics.benchmarks.HistogramBenchmark.simpleclient",
        "mode" : "thrpt",
        "threads" : 4,
        "forks" : 3,
        "jvm" : "/home/runner/.local/share/mise/installs/java/temurin-25.0.2+10.0.LTS/bin/java",
        "jvmArgs" : [
        ],
        "jdkVersion" : "25.0.2",
        "vmName" : "OpenJDK 64-Bit Server VM",
        "vmVersion" : "25.0.2+10-LTS",
        "warmupIterations" : 3,
        "warmupTime" : "10 s",
        "warmupBatchSize" : 1,
        "measurementIterations" : 5,
        "measurementTime" : "10 s",
        "measurementBatchSize" : 1,
        "primaryMetric" : {
            "score" : 4432.624525213379,
            "scoreError" : 155.91046200371937,
            "scoreConfidence" : [
                4276.714063209659,
                4588.534987217098
            ],
            "scorePercentiles" : {
                "0.0" : 4222.376043808828,
                "50.0" : 4511.572176032149,
                "90.0" : 4552.173590779633,
                "95.0" : 4553.062577770013,
                "99.0" : 4553.062577770013,
                "99.9" : 4553.062577770013,
                "99.99" : 4553.062577770013,
                "99.999" : 4553.062577770013,
                "99.9999" : 4553.062577770013,
                "100.0" : 4553.062577770013
            },
            "scoreUnit" : "ops/s",
            "rawData" : [
                [
                    4237.286637790658,
                    4222.376043808828,
                    4241.148939890414,
                    4237.366956217318,
                    4234.515081811651
                ],
                [
                    4538.725843058315,
                    4548.095404268543,
                    4549.658784912683,
                    4551.580932786046,
                    4553.062577770013
                ],
                [
                    4505.322942139759,
                    4508.482593190556,
                    4530.254338648754,
                    4511.572176032149,
                    4519.918625874984
                ]
            ]
        },
        "secondaryMetrics" : {
        }
    },
    {
        "jmhVersion" : "1.37",
        "benchmark" : "io.prometheus.metrics.benchmarks.TextFormatUtilBenchmark.openMetricsWriteToByteArray",
        "mode" : "thrpt",
        "threads" : 1,
        "forks" : 3,
        "jvm" : "/home/runner/.local/share/mise/installs/java/temurin-25.0.2+10.0.LTS/bin/java",
        "jvmArgs" : [
        ],
        "jdkVersion" : "25.0.2",
        "vmName" : "OpenJDK 64-Bit Server VM",
        "vmVersion" : "25.0.2+10-LTS",
        "warmupIterations" : 3,
        "warmupTime" : "10 s",
        "warmupBatchSize" : 1,
        "measurementIterations" : 5,
        "measurementTime" : "10 s",
        "measurementBatchSize" : 1,
        "primaryMetric" : {
            "score" : 439235.94156094996,
            "scoreError" : 5112.327971614899,
            "scoreConfidence" : [
                434123.61358933506,
                444348.26953256485
            ],
            "scorePercentiles" : {
                "0.0" : 431750.6540981733,
                "50.0" : 436783.15697327064,
                "90.0" : 446304.9717109694,
                "95.0" : 448143.05203493556,
                "99.0" : 448143.05203493556,
                "99.9" : 448143.05203493556,
                "99.99" : 448143.05203493556,
                "99.999" : 448143.05203493556,
                "99.9999" : 448143.05203493556,
                "100.0" : 448143.05203493556
            },
            "scoreUnit" : "ops/s",
            "rawData" : [
                [
                    435442.95822528325,
                    436077.5970586626,
                    442835.6363827572,
                    445042.5855182279,
                    448143.05203493556
                ],
                [
                    434970.976700042,
                    436536.0933422215,
                    435864.5409740645,
                    436783.15697327064,
                    443502.6669150053
                ],
                [
                    445079.58482832526,
                    440981.6222744287,
                    440125.8921943075,
                    431750.6540981733,
                    435402.1058945445
                ]
            ]
        },
        "secondaryMetrics" : {
        }
    },
    {
        "jmhVersion" : "1.37",
        "benchmark" : "io.prometheus.metrics.benchmarks.TextFormatUtilBenchmark.openMetricsWriteToNull",
        "mode" : "thrpt",
        "threads" : 1,
        "forks" : 3,
        "jvm" : "/home/runner/.local/share/mise/installs/java/temurin-25.0.2+10.0.LTS/bin/java",
        "jvmArgs" : [
        ],
        "jdkVersion" : "25.0.2",
        "vmName" : "OpenJDK 64-Bit Server VM",
        "vmVersion" : "25.0.2+10-LTS",
        "warmupIterations" : 3,
        "warmupTime" : "10 s",
        "warmupBatchSize" : 1,
        "measurementIterations" : 5,
        "measurementTime" : "10 s",
        "measurementBatchSize" : 1,
        "primaryMetric" : {
            "score" : 445903.23100591067,
            "scoreError" : 7281.632317969987,
            "scoreConfidence" : [
                438621.5986879407,
                453184.86332388065
            ],
            "scorePercentiles" : {
                "0.0" : 432922.8792100799,
                "50.0" : 445951.2140987687,
                "90.0" : 456369.0448464046,
                "95.0" : 457456.86234492034,
                "99.0" : 457456.86234492034,
                "99.9" : 457456.86234492034,
                "99.99" : 457456.86234492034,
                "99.999" : 457456.86234492034,
                "99.9999" : 457456.86234492034,
                "100.0" : 457456.86234492034
            },
            "scoreUnit" : "ops/s",
            "rawData" : [
                [
                    452360.2949034978,
                    446914.36119015806,
                    455643.83318072744,
                    457456.86234492034,
                    443620.1784366346
                ],
                [
                    449470.07728554006,
                    445315.243668199,
                    445951.2140987687,
                    444553.6345897469,
                    450291.64902647975
                ],
                [
                    436389.7803854758,
                    439692.37960471987,
                    448113.057960432,
                    439853.0192032794,
                    432922.8792100799
                ]
            ]
        },
        "secondaryMetrics" : {
        }
    },
    {
        "jmhVersion" : "1.37",
        "benchmark" : "io.prometheus.metrics.benchmarks.TextFormatUtilBenchmark.prometheusWriteToByteArray",
        "mode" : "thrpt",
        "threads" : 1,
        "forks" : 3,
        "jvm" : "/home/runner/.local/share/mise/installs/java/temurin-25.0.2+10.0.LTS/bin/java",
        "jvmArgs" : [
        ],
        "jdkVersion" : "25.0.2",
        "vmName" : "OpenJDK 64-Bit Server VM",
        "vmVersion" : "25.0.2+10-LTS",
        "warmupIterations" : 3,
        "warmupTime" : "10 s",
        "warmupBatchSize" : 1,
        "measurementIterations" : 5,
        "measurementTime" : "10 s",
        "measurementBatchSize" : 1,
        "primaryMetric" : {
            "score" : 443569.1553586458,
            "scoreError" : 14705.35075534848,
            "scoreConfidence" : [
                428863.8046032973,
                458274.5061139942
            ],
            "scorePercentiles" : {
                "0.0" : 403831.35630407324,
                "50.0" : 442546.63280897867,
                "90.0" : 459896.45974024554,
                "95.0" : 460329.477525643,
                "99.0" : 460329.477525643,
                "99.9" : 460329.477525643,
                "99.99" : 460329.477525643,
                "99.999" : 460329.477525643,
                "99.9999" : 460329.477525643,
                "100.0" : 460329.477525643
            },
            "scoreUnit" : "ops/s",
            "rawData" : [
                [
                    451323.96785578487,
                    441480.0396603007,
                    403831.35630407324,
                    436028.26676474005,
                    442056.408089045
                ],
                [
                    445047.95338767435,
                    457634.4976681558,
                    460329.477525643,
                    459607.78121664724,
                    454038.3933378391
                ],
                [
                    442546.63280897867,
                    441147.2141051672,
                    441504.7060454416,
                    442691.4449838283,
                    434269.19062636705
                ]
            ]
        },
        "secondaryMetrics" : {
        }
    },
    {
        "jmhVersion" : "1.37",
        "benchmark" : "io.prometheus.metrics.benchmarks.TextFormatUtilBenchmark.prometheusWriteToNull",
        "mode" : "thrpt",
        "threads" : 1,
        "forks" : 3,
        "jvm" : "/home/runner/.local/share/mise/installs/java/temurin-25.0.2+10.0.LTS/bin/java",
        "jvmArgs" : [
        ],
        "jdkVersion" : "25.0.2",
        "vmName" : "OpenJDK 64-Bit Server VM",
        "vmVersion" : "25.0.2+10-LTS",
        "warmupIterations" : 3,
        "warmupTime" : "10 s",
        "warmupBatchSize" : 1,
        "measurementIterations" : 5,
        "measurementTime" : "10 s",
        "measurementBatchSize" : 1,
        "primaryMetric" : {
            "score" : 461448.10059202014,
            "scoreError" : 16799.623359443944,
            "scoreConfidence" : [
                444648.4772325762,
                478247.7239514641
            ],
            "scorePercentiles" : {
                "0.0" : 436656.66184255184,
                "50.0" : 462757.7567670076,
                "90.0" : 481116.88727152353,
                "95.0" : 482483.66503628605,
                "99.0" : 482483.66503628605,
                "99.9" : 482483.66503628605,
                "99.99" : 482483.66503628605,
                "99.999" : 482483.66503628605,
                "99.9999" : 482483.66503628605,
                "100.0" : 482483.66503628605
            },
            "scoreUnit" : "ops/s",
            "rawData" : [
                [
                    449363.58571954246,
                    452665.2535598004,
                    462757.7567670076,
                    474922.71533308004,
                    471412.0876577573
                ],
                [
                    455369.7561361722,
                    442526.62586924736,
                    437549.21323817834,
                    436656.66184255184,
                    452924.21461767587
                ],
                [
                    473000.40807507763,
                    473197.5929652596,
                    482483.66503628605,
                    480205.7020950152,
                    476686.2699676518
                ]
            ]
        },
        "secondaryMetrics" : {
        }
    }
]


